slapos.toolbox-0.159-py3.11-nspkg.pth
slapos/apachedex.py
slapos/backup_signature.py
slapos/cachechecker.py
slapos/checkfeedaspromise.py
slapos/dnsresolver.py
slapos/generatefeed.py
slapos/htpasswd.py
slapos/loganalyze.py
slapos/onetimedownload.py
slapos/securedelete.py
slapos/systool.py
slapos/zodbpack.py
slapos/agent/__init__.py
slapos/agent/agent.py
slapos/agent/tester.py
slapos/container/__init__.py
slapos/container/process.py
slapos/equeue/__init__.py
slapos/lamp/__init__.py
slapos/monitor/__init__.py
slapos/monitor/build_statistic.py
slapos/monitor/collect.py
slapos/monitor/globalstate.py
slapos/monitor/monitor.py
slapos/monitor/monitor_config_write.py
slapos/monitor/runpromise.py
slapos/networkbench/__init__.py
slapos/networkbench/ping.py
slapos/onetimeupload/__init__.py
slapos/onetimeupload/templates/badkey.html
slapos/onetimeupload/templates/done.html
slapos/onetimeupload/templates/index.html
slapos/promise/__init__.py
slapos/promise/apache_mpm_watchdog/__init__.py
slapos/promise/check_apachedex_result/__init__.py
slapos/promise/check_computer_memory/__init__.py
slapos/promise/check_slow_queries_digest_result/__init__.py
slapos/promise/check_user_memory/__init__.py
slapos/promise/is_local_tcp_port_opened/__init__.py
slapos/promise/is_process_older_than_dependency_set/__init__.py
slapos/promise/plugin/__init__.py
slapos/promise/plugin/backupserver_check_backup.py
slapos/promise/plugin/check_amarisoft_stats_log.py
slapos/promise/plugin/check_baseband_latency.py
slapos/promise/plugin/check_certificate.py
slapos/promise/plugin/check_command_execute.py
slapos/promise/plugin/check_cpri_lock.py
slapos/promise/plugin/check_cpu_temperature.py
slapos/promise/plugin/check_error_on_http_log.py
slapos/promise/plugin/check_error_on_zope_longrequest_log.py
slapos/promise/plugin/check_file_state.py
slapos/promise/plugin/check_free_disk_space.py
slapos/promise/plugin/check_frequency_outofbounds.py
slapos/promise/plugin/check_gps_lock.py
slapos_toolbox-0.159.dist-info/METADATA
slapos_toolbox-0.159.dist-info/WHEEL
slapos_toolbox-0.159.dist-info/entry_points.txt
slapos_toolbox-0.159.dist-info/namespace_packages.txt
slapos_toolbox-0.159.dist-info/top_level.txt
slapos_toolbox-0.159.dist-info/RECORD
