Metadata-Version: 2.4
Name: slapos.toolbox
Version: 0.159
Summary: SlapOS toolbox.
Home-page: https://lab.nexedi.com/nexedi/slapos.toolbox
Maintainer: Nexedi
Maintainer-email: info@nexedi.com
License: GPLv3
Keywords: slapos toolbox
Classifier: Programming Language :: Python
Requires-Python: >=3.8
Requires-Dist: Flask
Requires-Dist: atomize
Requires-Dist: feedparser
Requires-Dist: lockfile
Requires-Dist: lxml
Requires-Dist: psutil
Requires-Dist: setuptools
Requires-Dist: slapos.core
Requires-Dist: xml_marshaller
Requires-Dist: croniter
Requires-Dist: pytz
Requires-Dist: tzlocal
Requires-Dist: netifaces
Requires-Dist: erp5.util
Requires-Dist: PyRSS2Gen
Requires-Dist: dnspython
Requires-Dist: requests
Requires-Dist: zc.buildout
Requires-Dist: six
Requires-Dist: pyasn1-modules
Requires-Dist: click
Requires-Dist: websocket-client
Provides-Extra: lampconfigure
Requires-Dist: mysqlclient; extra == "lampconfigure"
Provides-Extra: zodbpack
Requires-Dist: ZODB3; extra == "zodbpack"
Provides-Extra: flask-auth
Requires-Dist: Flask-Auth; extra == "flask-auth"
Provides-Extra: pandas
Requires-Dist: pandas; extra == "pandas"
Provides-Extra: prediction
Requires-Dist: statsmodels>=0.14.0; extra == "prediction"
Requires-Dist: scipy; extra == "prediction"
Requires-Dist: pandas; extra == "prediction"
Provides-Extra: test
Requires-Dist: cryptography; extra == "test"
Requires-Dist: jsonschema; extra == "test"
Requires-Dist: mock; extra == "test"
Requires-Dist: websockets; extra == "test"
Requires-Dist: statsmodels>=0.14.0; extra == "test"
Requires-Dist: scipy; extra == "test"
Requires-Dist: pandas; extra == "test"
Dynamic: classifier
Dynamic: description
Dynamic: description-content-type
Dynamic: home-page
Dynamic: keywords
Dynamic: license
Dynamic: maintainer
Dynamic: maintainer-email
Dynamic: provides-extra
Dynamic: requires-dist
Dynamic: requires-python
Dynamic: summary
